bin/convert-lora-to-ggml.py
bin/convert.py
bin/ggml-metal.metal
bin/llava-cli
ctransformer_core/__init__.py
ctransformer_core/__main__.py
ctransformer_core/_internals.py
ctransformer_core/_logger.py
ctransformer_core/_utils.py
ctransformer_core/ggml-metal.metal
ctransformer_core/libllama.dylib
ctransformer_core/libllava.dylib
ctransformer_core/llama.py
ctransformer_core/llama_cache.py
ctransformer_core/llama_chat_format.py
ctransformer_core/llama_cpp.py
ctransformer_core/llama_grammar.py
ctransformer_core/llama_speculative.py
ctransformer_core/llama_types.py
ctransformer_core/llava_cpp.py
ctransformer_core/logo.png
include/ggml-alloc.h
include/ggml-backend.h
include/ggml-metal.h
include/ggml.h
include/llama.h
lib/cmake/Llama/LlamaConfig.cmake
lib/cmake/Llama/LlamaConfigVersion.cmake
lib/libggml_shared.dylib
lib/libllama.dylib
lib/libllava.dylib
ctransformer_core-0.2.28.dist-info/METADATA
ctransformer_core-0.2.28.dist-info/WHEEL
ctransformer_core-0.2.28.dist-info/entry_points.txt
ctransformer_core-0.2.28.dist-info/licenses/LICENSE.md
ctransformer_core-0.2.28.dist-info/RECORD
