Metadata-Version: 2.1
Name: ctransformer_core
Version: 0.2.28
Summary: gguf connector core built on ctransformers
Author-Email: calcuis <calculatics@gmail.com>
License: MIT
Classifier: Intended Audience :: Developers
Classifier: Intended Audience :: Education
Classifier: Intended Audience :: Science/Research
Classifier: License :: OSI Approved :: MIT License
Classifier: Programming Language :: Python :: 3
Classifier: Topic :: Scientific/Engineering
Classifier: Topic :: Scientific/Engineering :: Mathematics
Classifier: Topic :: Scientific/Engineering :: Artificial Intelligence
Classifier: Topic :: Software Development
Classifier: Topic :: Software Development :: Libraries
Classifier: Topic :: Software Development :: Libraries :: Python Modules
Project-URL: Homepage, https://github.com/calcuis/ctransformer-core
Project-URL: Issues, https://github.com/calcuis/ctransformer-core/issues
Requires-Python: >=3.8
Requires-Dist: typing-extensions>=4.5.0
Requires-Dist: numpy>=1.20.0
Requires-Dist: diskcache>=5.6.1
Requires-Dist: jinja2>=2.11.3
License-File: LICENSE.md
